django_registries/__about__.py
django_registries/__init__.py
django_registries/apps.py
django_registries/py.typed
django_registries/registry.py
django_registries-0.0.4.dist-info/METADATA
django_registries-0.0.4.dist-info/WHEEL
django_registries-0.0.4.dist-info/licenses/LICENSE.txt
django_registries-0.0.4.dist-info/RECORD
