Metadata-Version: 2.4
Name: django-registries
Version: 0.0.4
Summary: django-registries is a structured way to create registries of implementations.
Project-URL: Documentation, https://django-registries.readthedocs.io/
Project-URL: Issues, https://github.com/valberg/django-registries/issues
Project-URL: Source, https://github.com/valberg/django-registries
Author-email: Víðir Valberg Guðmundsson <valberg@orn.li>
License-Expression: MIT
License-File: LICENSE.txt
Classifier: Development Status :: 3 - Alpha
Classifier: Programming Language :: Python
Classifier: Programming Language :: Python :: 3.9
Classifier: Programming Language :: Python :: 3.10
Classifier: Programming Language :: Python :: 3.11
Classifier: Programming Language :: Python :: Implementation :: CPython
Classifier: Programming Language :: Python :: Implementation :: PyPy
Requires-Python: >=3.9
Requires-Dist: django>=3.2
